Metadata-Version: 2.1
Name: UniversalTranslator-evalir
Version: 0.0.10
Summary: Parses a file with a certain structure and converts to the desired metric unit.
Home-page: https://github.com/Evalir/UniversalTranslator
Author: Enrique Ortiz
Author-email: hi.evalir@gmail.com
License: UNKNOWN
Platform: UNKNOWN
Classifier: Programming Language :: Python :: 3
Classifier: License :: OSI Approved :: GNU General Public License v3 or later (GPLv3+)
Classifier: Operating System :: OS Independent
